resmetric/__init__.py
resmetric/cli.py
resmetric/metrics.py
resmetric/plot.py
resmetric-1.0.0rc31.dist-info/licenses/LICENSE.txt
resmetric-1.0.0rc31.dist-info/METADATA
resmetric-1.0.0rc31.dist-info/WHEEL
resmetric-1.0.0rc31.dist-info/entry_points.txt
resmetric-1.0.0rc31.dist-info/top_level.txt
resmetric-1.0.0rc31.dist-info/RECORD
