Metadata-Version: 2.4
Name: resmetric
Version: 1.0.0rc31
Summary: Explore and visualize resilience metrics and antifragility in performance graphs of self-adaptive systems.
Home-page: https://github.com/ferdinand-koenig/resmetric
Author: Ferdinand Koenig
Author-email: ferdinand@koenix.de
Classifier: Programming Language :: Python :: 3
Classifier: Programming Language :: Python :: 3.8
Classifier: Programming Language :: Python :: 3.9
Classifier: Programming Language :: Python :: 3.10
Classifier: Programming Language :: Python :: 3.11
Classifier: Programming Language :: Python :: 3.12
Classifier: Programming Language :: Python :: 3.13
Classifier: Operating System :: OS Independent
Classifier: Topic :: Scientific/Engineering
Classifier: Topic :: Scientific/Engineering :: Visualization
Requires-Python: >=3.8, <4
License-File: LICENSE.txt
Requires-Dist: plotly<6.0.0,>=5.23.0
Requires-Dist: numpy>=1.23.5
Requires-Dist: scipy>=1.10.1
Requires-Dist: scikit-optimize>=0.10.2
Requires-Dist: pwlf>=2.2.1
Dynamic: author
Dynamic: author-email
Dynamic: classifier
Dynamic: description
Dynamic: description-content-type
Dynamic: home-page
Dynamic: license-file
Dynamic: requires-dist
Dynamic: requires-python
Dynamic: summary
